LICENSE
README.md
setup.py
andrew_fib_py.egg-info/PKG-INFO
andrew_fib_py.egg-info/SOURCES.txt
andrew_fib_py.egg-info/dependency_links.txt
andrew_fib_py.egg-info/entry_points.txt
andrew_fib_py.egg-info/top_level.txt
fib_py/__init__.py
fib_py/cmd/__init__.py
fib_py/cmd/fib_number.py
fib_py/fib_calcs/__init__.py
fib_py/fib_calcs/fib_number.py
fib_py/fib_calcs/fib_numbers.py
tests/fib_py/__init__.py
tests/fib_py/fib_calcs/__init__.py
tests/fib_py/fib_calcs/test_fib_number.py
tests/fib_py/fib_calcs/test_fib_numbers.py